aek_img_trainer/__init__.py
aek_img_trainer/trainer.py
aek_img_trainer-1.0.0.dist-info/licenses/LICENSE
aek_img_trainer-1.0.0.dist-info/METADATA
aek_img_trainer-1.0.0.dist-info/WHEEL
aek_img_trainer-1.0.0.dist-info/top_level.txt
aek_img_trainer-1.0.0.dist-info/RECORD
