Metadata-Version: 2.4
Name: aek-img-trainer
Version: 1.0.0
Summary: Image classification trainer using OpenCV and timm
Author: Alp Emre Karaahmet
Author-email: alpemrekaraahmet@gmail.com
Classifier: Programming Language :: Python :: 3
Classifier: License :: OSI Approved :: MIT License
Requires-Python: >=3.7
License-File: LICENSE
Requires-Dist: torch
Requires-Dist: opencv-python
Requires-Dist: numpy
Requires-Dist: timm
Requires-Dist: openvino
Dynamic: author
Dynamic: author-email
Dynamic: classifier
Dynamic: description
Dynamic: description-content-type
Dynamic: license-file
Dynamic: requires-dist
Dynamic: requires-python
Dynamic: summary
